setup.py
hdv_emails/__init__.py
hdv_emails/mail.py
hdv_emails.egg-info/PKG-INFO
hdv_emails.egg-info/SOURCES.txt
hdv_emails.egg-info/dependency_links.txt
hdv_emails.egg-info/requires.txt
hdv_emails.egg-info/top_level.txt