Metadata-Version: 1.1
Name: hdv-emails
Version: 0.0.1
Summary: Simple wrapper class for emails
Home-page: https://github.com/jk43/hdv_emails
Author: Alex Hyojun Kim
Author-email: alex@hotdev.com
License: BSD
Download-URL: https://github.com/jk43/hdv_emails.git
Platform: UNKNOWN
